scrying/__init__.py
scrying/main.py
scrying-0.1.2.dist-info/LICENSE
scrying-0.1.2.dist-info/METADATA
scrying-0.1.2.dist-info/WHEEL
scrying-0.1.2.dist-info/top_level.txt
scrying-0.1.2.dist-info/RECORD
