Metadata-Version: 2.1
Name: scrying
Version: 0.1.2
Summary: A ScryfallAPI port written in Python
Home-page: https://github.com/chumpblocckami/scrying
Author: Matteo Mazzola
Author-email: contact.matteomazzola@gmail.com
License: BSD 2-clause
Classifier: Development Status :: 1 - Planning
Classifier: Intended Audience :: Science/Research
Classifier: License :: OSI Approved :: BSD License
Classifier: Operating System :: POSIX :: Linux
Classifier: Programming Language :: Python :: 2
Classifier: Programming Language :: Python :: 2.7
Classifier: Programming Language :: Python :: 3
Classifier: Programming Language :: Python :: 3.4
Classifier: Programming Language :: Python :: 3.5
License-File: LICENSE
Requires-Dist: requests
Requires-Dist: pillow
Requires-Dist: tqdm
